[
  {
    "participant_id": "3a27d301-4786-4839-8003-3a6cabdd838d",
    "problem_id": "ba9e00da-a44d-42f4-9bb2-d2a92ff73852",
    "verdict": "AC",
    "score": 100,
    "submitted_at": "2026-03-09T15:23:46.992965+00:00",
    "participants": {
      "name": "Jagannath Ladane",
      "college": "PCCOE"
    }
  },
  {
    "participant_id": "3a27d301-4786-4839-8003-3a6cabdd838d",
    "problem_id": "6d6cfe87-8216-4e51-8169-84e34ec6d5f1",
    "verdict": "AC",
    "score": 100,
    "submitted_at": "2026-03-09T15:26:30.028579+00:00",
    "participants": {
      "name": "Jagannath Ladane",
      "college": "PCCOE"
    }
  },
  {
    "participant_id": "3a27d301-4786-4839-8003-3a6cabdd838d",
    "problem_id": "6d6cfe87-8216-4e51-8169-84e34ec6d5f1",
    "verdict": "AC",
    "score": 100,
    "submitted_at": "2026-03-09T15:27:04.535454+00:00",
    "participants": {
      "name": "Jagannath Ladane",
      "college": "PCCOE"
    }
  },
  {
    "participant_id": "3a27d301-4786-4839-8003-3a6cabdd838d",
    "problem_id": "6d6cfe87-8216-4e51-8169-84e34ec6d5f1",
    "verdict": "AC",
    "score": 100,
    "submitted_at": "2026-03-09T15:27:48.105189+00:00",
    "participants": {
      "name": "Jagannath Ladane",
      "college": "PCCOE"
    }
  },
  {
    "participant_id": "3a27d301-4786-4839-8003-3a6cabdd838d",
    "problem_id": "ba9e00da-a44d-42f4-9bb2-d2a92ff73852",
    "verdict": "AC",
    "score": 100,
    "submitted_at": "2026-03-09T15:31:02.938218+00:00",
    "participants": {
      "name": "Jagannath Ladane",
      "college": "PCCOE"
    }
  },
  {
    "participant_id": "3a27d301-4786-4839-8003-3a6cabdd838d",
    "problem_id": "6d6cfe87-8216-4e51-8169-84e34ec6d5f1",
    "verdict": "AC",
    "score": 100,
    "submitted_at": "2026-03-09T15:31:15.518232+00:00",
    "participants": {
      "name": "Jagannath Ladane",
      "college": "PCCOE"
    }
  },
  {
    "participant_id": "3a27d301-4786-4839-8003-3a6cabdd838d",
    "problem_id": "ba9e00da-a44d-42f4-9bb2-d2a92ff73852",
    "verdict": "AC",
    "score": 100,
    "submitted_at": "2026-03-09T16:40:54.441883+00:00",
    "participants": {
      "name": "Jagannath Ladane",
      "college": "PCCOE"
    }
  },
  {
    "participant_id": "3a27d301-4786-4839-8003-3a6cabdd838d",
    "problem_id": "ba9e00da-a44d-42f4-9bb2-d2a92ff73852",
    "verdict": "WA",
    "score": 0,
    "submitted_at": "2026-03-09T16:41:48.002047+00:00",
    "participants": {
      "name": "Jagannath Ladane",
      "college": "PCCOE"
    }
  }
]